rsync_backup/__init__.py
rsync_backup/__main__.py
rsync_backup/rsync.py
backup_with_rsync-0.9.2.dist-info/METADATA
backup_with_rsync-0.9.2.dist-info/WHEEL
backup_with_rsync-0.9.2.dist-info/entry_points.txt
backup_with_rsync-0.9.2.dist-info/top_level.txt
backup_with_rsync-0.9.2.dist-info/RECORD
