Metadata-Version: 2.1
Name: backup-with-rsync
Version: 0.9.2
Summary: Simple backup wrapper with configuration over rsync for regularly backing up via command line.
Home-page: https://github.com/akshaybadola/backup-with-rsync
Author: Akshay Badola
License: MIT
Keywords: rsync backup
Classifier: Development Status :: 4 - Beta
Classifier: Intended Audience :: Developers
Classifier: Intended Audience :: End Users/Desktop
Classifier: License :: OSI Approved :: MIT License
Classifier: Topic :: System :: Archiving :: Backup
Classifier: Topic :: System :: Networking
Classifier: Programming Language :: Python :: 3.7
Classifier: Programming Language :: Python :: 3.8
Classifier: Programming Language :: Python :: 3.9
Classifier: Natural Language :: English
Requires-Python: >=3.7, <=4.0
Requires-Dist: PyYAML
